symbex/__init__.py
symbex/__main__.py
symbex/cli.py
symbex/lib.py
symbex-2.0.dist-info/licenses/LICENSE
symbex-2.0.dist-info/METADATA
symbex-2.0.dist-info/WHEEL
symbex-2.0.dist-info/entry_points.txt
symbex-2.0.dist-info/top_level.txt
symbex-2.0.dist-info/RECORD
