Metadata-Version: 2.4
Name: symbex
Version: 2.0
Summary: Find the Python code for specified symbols
Author: Simon Willison
License-Expression: Apache-2.0
Project-URL: Homepage, https://github.com/simonw/symbex
Project-URL: Issues, https://github.com/simonw/symbex/issues
Project-URL: CI, https://github.com/simonw/symbex/actions
Project-URL: Changelog, https://github.com/simonw/symbex/releases
Requires-Python: >=3.8
License-File: LICENSE
Requires-Dist: click
Provides-Extra: test
Requires-Dist: pytest; extra == "test"
Requires-Dist: pytest-icdiff; extra == "test"
Requires-Dist: cogapp; extra == "test"
Requires-Dist: PyYAML; extra == "test"
Requires-Dist: ruff; extra == "test"
Dynamic: license-file
